wordfreq_cn/__init__.py
wordfreq_cn/cli.py
wordfreq_cn/core.py
wordfreq_cn/data/__init__.py
wordfreq_cn/data/cn_stopwords.txt
wordfreq_cn/data/fonts/SourceHanSansHWSC-VF.ttf
wordfreq_cn/data/fonts/__init__.py
wordfreq_cn-0.1.10.dist-info/METADATA
wordfreq_cn-0.1.10.dist-info/WHEEL
wordfreq_cn-0.1.10.dist-info/entry_points.txt
wordfreq_cn-0.1.10.dist-info/top_level.txt
wordfreq_cn-0.1.10.dist-info/RECORD
