Metadata-Version: 2.4
Name: wordfreq-cn
Version: 0.1.10
Summary: 中文新闻词频分析与趋势词云工具
Author-email: likanug <likanug.g@qq.com>
License-Expression: MIT
Requires-Python: >=3.12
Requires-Dist: scikit-learn>=1.7.2
Requires-Dist: wordcloud>=1.9.4
Requires-Dist: numpy>=2.3.5
Requires-Dist: contractions>=0.1.73
Requires-Dist: spacy-pkuseg>=1.0.1
Provides-Extra: test
Requires-Dist: pytest>=9.0; extra == "test"
Requires-Dist: pytest-mock>=3.0; extra == "test"
Requires-Dist: pytest-cov>=4.0; extra == "test"
